scbw/__init__.py
scbw/__main__.py
scbw/bot_factory.py
scbw/bot_storage.py
scbw/bwapi.py
scbw/cli.py
scbw/defaults.py
scbw/docker.py
scbw/error.py
scbw/game.py
scbw/game_type.py
scbw/install.py
scbw/logs.py
scbw/map.py
scbw/player.py
scbw/plot.py
scbw/result.py
scbw/utils.py
scbw/vnc.py
scbw/local_docker/game.dockerfile
scbw/local_docker/player.mpc
scbw/local_docker/player.spc
scbw_dev-0.2b11.dist-info/DESCRIPTION.rst
scbw_dev-0.2b11.dist-info/LICENSE.txt
scbw_dev-0.2b11.dist-info/METADATA
scbw_dev-0.2b11.dist-info/RECORD
scbw_dev-0.2b11.dist-info/WHEEL
scbw_dev-0.2b11.dist-info/entry_points.txt
scbw_dev-0.2b11.dist-info/metadata.json
scbw_dev-0.2b11.dist-info/top_level.txt
