Metadata-Version: 2.0
Name: scbw-dev
Version: 0.2b11
Summary: Multi-platform Version of StarCraft: Brood War in a Docker Container
Home-page: https://github.com/Games-and-Simulations/sc-docker
Author: Michal Sustr
Author-email: michal.sustr@aic.fel.cvut.cz
License: UNKNOWN
Keywords: starcraft docker broodwar ai bot
Platform: UNKNOWN
Classifier: Development Status :: 4 - Beta
Classifier: Intended Audience :: Developers
Classifier: Topic :: Software Development :: Build Tools
Classifier: License :: OSI Approved :: MIT License
Classifier: Programming Language :: Python :: 3.4
Requires-Python: >=3.4
Requires-Dist: requests
Requires-Dist: coloredlogs
Requires-Dist: numpy
Requires-Dist: tqdm
Requires-Dist: requests
Requires-Dist: python-dateutil
Requires-Dist: pandas
Requires-Dist: matplotlib
